{
    "nodes": [
        {
            "parameters": {
                "rule": {
                    "interval": [
                        {
                            "field": "cronExpression",
                            "expression": "10 8 * * *"
                        },
                        {
                            "field": "cronExpression",
                            "expression": "50 15 * * *"
                        },
                        {
                            "field": "cronExpression",
                            "expression": "10 18 * * *"
                        }
                    ]
                }
            },
            "id": "schedule-trigger-node",
            "name": "Schedule Trigger",
            "type": "n8n-nodes-base.scheduleTrigger",
            "typeVersion": 1,
            "position": [250, 300]
        }
    ],
    "connections": {},
    "settings": {}
}